bitsight/__init__.py
bitsight/api_io/__init__.py
bitsight/api_io/request_handler.py
bitsight/resources/__init__.py
bitsight/resources/alerts.py
bitsight/resources/bitsight.py
bitsight/resources/companies.py
bitsight/resources/company_requests.py
bitsight/resources/portfolio.py
bitsight/resources/reports.py
bitsight/resources/rua.py
bitsight/resources/subscriptions.py
bitsight-0.2.4.dist-info/licenses/LICENSE
bitsight-0.2.4.dist-info/METADATA
bitsight-0.2.4.dist-info/WHEEL
bitsight-0.2.4.dist-info/top_level.txt
bitsight-0.2.4.dist-info/RECORD
