Metadata-Version: 2.4
Name: bitsight
Version: 0.2.4
Summary: Unofficial Package for BitSight's API
Home-page: https://github.com/brandon-smith-187/bitsight
Author: Brandon Smith
Author-email: bcsmith2@gmail.com
License: MIT
Requires-Python: >=3.7
License-File: LICENSE
Requires-Dist: requests>=2.28.1
Dynamic: author
Dynamic: author-email
Dynamic: description
Dynamic: description-content-type
Dynamic: home-page
Dynamic: license
Dynamic: license-file
Dynamic: requires-dist
Dynamic: requires-python
Dynamic: summary
